[
    { "src": "music/lofi/Veil.mp3", "title": "Veil", "artist": "Tem.Polor", "album": "Lofi Classics" },
    { "src": "music/lofi/Wandering Through City Lights.mp3", "title": "Wandering Through City Lights", "artist": "Tem.Polor", "album": "Lofi Classics" },
    { "src": "music/lofi/Waves of Serenity.mp3", "title": "Waves of Serenity", "artist": "Tem.Polor", "album": "Lofi Classics" },
    { "src": "music/lofi/Euphoria.mp3", "title": "Euphoria", "artist": "Tem.Polor", "album": "Lofi Classics" }
]